[
  {
    "date": "2025年10月27日",
    "text": "🌟 Li's Meet Pro 每日健身小提醒｜2025年10月27日\n· · · · ·\n1️⃣ 輕鬆伸展關節，喚醒身體活力 😌\n• 每天動一動，關節不僵硬\n• 伸展肩頸手腕，放鬆工作壓力\n• 緩慢輕柔伸展，避免過度拉扯\n2️⃣ 調整良好站姿坐姿，告別痠痛 🧘\n• 坐挺不駝背，腰背壓力小\n• 站立重心穩，雙腳平均分擔\n• 手機不低頭，保護頸椎健康\n \n把好習慣從今天開始！ ✅\n你的專屬教練 李詩民 提醒您。\n預約與補課系統 👉 https://lms-booking-pro-5467.vercel.app/"
  },
  {
    "date": "2025年10月28日",
    "text": "🌟 Li's Meet Pro 每日健身小提醒｜2025年10月28日\n· · · · ·\n1️⃣ 核心有感啟動，告別腰痠背痛！ 💪\n• 坐直輕收腹，肚臍往內拉\n• 感覺腹部微繃，不是憋氣\n• 隨時練習，站坐都適用\n2️⃣ 正確坐姿，保護脊椎不費力！ 🧘\n• 雙腳平放地面，膝蓋呈90度\n• 臀部坐滿椅面，背部靠好\n• 螢幕與視線齊平，肩膀放鬆\n \n小步快走，持續最重要！ 🏁\n你的專屬教練 李詩民 提醒您。\n預約與補課系統 👉 https://lms-booking-pro-5467.vercel.app/"
  },
  {
    "date": "2025年10月29日",
    "text": "🌟 Li's Meet Pro 每日健身小提醒｜2025年10月29日\n· · · · ·\n1️⃣ 深蹲鍛鍊下半身 強化生活行動力 💪\n• 鍛鍊腿臀肌群\n• 提升全身穩定性\n• 日常活動更輕鬆\n2️⃣ 掌握深蹲小撇步 居家訓練輕鬆上手 🚶‍♀️\n• 腳與肩同寬站立\n• 想像坐下椅子般\n• 膝蓋不超過腳尖\n\n給自己 5 分鐘，立刻動起來！ ⏱️\n你的專屬教練 李詩民 提醒您。\n預約與補課系統 👉 https://lms-booking-pro-5467.vercel.app/"
  },
  {
    "date": "2025年10月30日",
    "text": "🌟 Li's Meet Pro 每日健身小提醒｜2025年10月30日\n· · · · ·\n1️⃣ 深呼吸啟動身心，一夜好眠 😌\n• 睡前慢吸慢吐，壓力消散。\n• 專注感受氣息，幫助入睡。\n• 練習腹式呼吸，深層放鬆。\n2️⃣ 打造睡前儀式，提升睡眠品質 🧘\n• 睡前一小時，遠離藍光。\n• 保持臥室黑暗，溫度適中。\n• 固定作息時間，身體習慣。\n \n把好習慣從今天開始！ ✅\n你的專屬教練 李詩民 提醒您。\n預約與補課系統 👉 https://lms-booking-pro-5467.vercel.app/"
  },
  {
    "date": "2025年10月31日",
    "text": "🌟 Li's Meet Pro 每日健身小提醒｜2025年10月31日\n· · · · ·\n1️⃣ 喚醒心肺活力，輕盈動起來！🔥\n• 輕柔暖身，準備迎接挑戰。\n• 讓心跳加速，感受活力。\n• 深呼吸，讓身體充滿氧氣。\n2️⃣ 智慧步行法，輕鬆走得更遠！🚶‍♀️\n• 姿態正確，保護關節。\n• 小步快走，增加燃脂。\n• 享受戶外，減輕壓力。\n \n現在就開始行動吧！ 💯🚀\n你的專屬教練 李詩民 提醒您。\n預約與補課系統 👉 https://lms-booking-pro-5467.vercel.app/"
  },
  {
    "date": "2025年11月01日",
    "text": "🌟 Li's Meet Pro 每日健身小提醒｜2025年11月01日\n· · · · ·\n1️⃣ 週末輕動找回活力，緩解肌肉疲勞 😌\n• 散步或伸展，放鬆身心\n• 促進血液循環，加速修復\n• 輕柔運動，為下週儲能\n2️⃣ 低強度運動緩解壓力，享受寧靜時光 🧘\n• 瑜珈或冥想，放鬆心情\n• 減少身體負擔，提升專注\n• 調整呼吸，舒緩壓力\n小步快走，持續最重要！ 🏁\n你的專屬教練 李詩民 提醒您。\n預約與補課系統 👉 https://lms-booking-pro-5467.vercel.app/"
  },
  {
    "date": "2025年11月02日",
    "text": "🌟 Li's Meet Pro 每日健身小提醒｜2025年11月02日\n· · · · ·\n1️⃣ 水分是身體引擎的汽油 💪\n• 喝水助燃燒脂肪 🔥\n• 提升身體機能運作效能\n• 排除體內廢物與毒素\n2️⃣ 聰明喝水，生活動能滿滿 🚶‍♀️\n• 起床一杯水喚醒身體\n• 餐前喝水助控制食慾\n• 運動前後別忘補充水\n \n把好習慣從今天開始！ ✅\n你的專屬教練 李詩民 提醒您。\n預約與補課系統 👉 https://lms-booking-pro-5467.vercel.app/"
  }
]